syscred/__init__.py
syscred/api_clients.py
syscred/backend_app.py
syscred/config.py
syscred/database.py
syscred/debug_factcheck.py
syscred/debug_graph_json.py
syscred/debug_init.py
syscred/debug_local_server.py
syscred/diagnose_imports.py
syscred/eval_metrics.py
syscred/graph_rag.py
syscred/ir_engine.py
syscred/ontology_manager.py
syscred/run_benchmark.py
syscred/seo_analyzer.py
syscred/setup.py
syscred/test_graphrag.py
syscred/test_phase1.py
syscred/test_phase2.py
syscred/test_suite.py
syscred/verification_system.py
syscred-2.2.1.dist-info/licenses/LICENSE
syscred-2.2.1.dist-info/METADATA
syscred-2.2.1.dist-info/WHEEL
syscred-2.2.1.dist-info/entry_points.txt
syscred-2.2.1.dist-info/top_level.txt
syscred-2.2.1.dist-info/RECORD
