Metadata-Version: 2.4
Name: syscred
Version: 2.2.1
Summary: A Neuro-Symbolic AI System for Information Credibility Verification
Author-email: "Dominique S. Loyer" <loyer.dominique@uqam.ca>
Project-URL: Homepage, https://github.com/DominiqueLoyer/systemFactChecking
Project-URL: Repository, https://github.com/DominiqueLoyer/systemFactChecking
Project-URL: Documentation, https://github.com/DominiqueLoyer/systemFactChecking/tree/main/03_Docs
Project-URL: Bug Tracker, https://github.com/DominiqueLoyer/systemFactChecking/issues
Project-URL: Zenodo, https://doi.org/10.5281/zenodo.17943226
Project-URL: Sponsor, https://github.com/sponsors/DominiqueLoyer
Keywords: fact-checking,credibility,information-verification,neuro-symbolic-ai,ontology,nlp,explainable-ai
Classifier: Development Status :: 4 - Beta
Classifier: Intended Audience :: Science/Research
Classifier: Topic :: Scientific/Engineering :: Artificial Intelligence
Classifier: License :: OSI Approved :: MIT License
Classifier: Programming Language :: Python :: 3
Classifier: Programming Language :: Python :: 3.8
Classifier: Programming Language :: Python :: 3.9
Classifier: Programming Language :: Python :: 3.10
Classifier: Programming Language :: Python :: 3.11
Classifier: Operating System :: OS Independent
Requires-Python: >=3.8
License-File: LICENSE
Requires-Dist: requests>=2.28.0
Requires-Dist: beautifulsoup4>=4.11.0
Requires-Dist: python-whois>=0.8.0
Requires-Dist: rdflib>=6.0.0
Requires-Dist: flask>=2.3.0
Requires-Dist: flask-cors>=4.0.0
Requires-Dist: python-dotenv>=1.0.0
Requires-Dist: pandas>=2.0.0
Provides-Extra: ml
Requires-Dist: torch>=2.0.0; extra == "ml"
Requires-Dist: transformers>=4.30.0; extra == "ml"
Requires-Dist: sentence-transformers>=2.2.0; extra == "ml"
Requires-Dist: numpy>=1.24.0; extra == "ml"
Requires-Dist: lime>=0.2.0; extra == "ml"
Provides-Extra: production
Requires-Dist: gunicorn>=20.1.0; extra == "production"
Requires-Dist: psycopg2-binary>=2.9.0; extra == "production"
Requires-Dist: flask-sqlalchemy>=3.0.0; extra == "production"
Provides-Extra: dev
Requires-Dist: pytest>=7.0.0; extra == "dev"
Requires-Dist: pytest-cov>=4.0.0; extra == "dev"
Requires-Dist: black>=23.0.0; extra == "dev"
Requires-Dist: flake8>=6.0.0; extra == "dev"
Requires-Dist: mypy>=1.0.0; extra == "dev"
Provides-Extra: all
Requires-Dist: syscred[ml]; extra == "all"
Requires-Dist: syscred[production]; extra == "all"
Requires-Dist: syscred[dev]; extra == "all"
Dynamic: license-file
